mosaik_gridcontrollers/__init__.py
mosaik_gridcontrollers/TransformerTapControlSingleNode/Model.py
mosaik_gridcontrollers/TransformerTapControlSingleNode/Simulator.py
mosaik_gridcontrollers/TransformerTapControlSingleNode/__init__.py
mosaik_gridcontrollers-0.3.dist-info/LICENSE.txt
mosaik_gridcontrollers-0.3.dist-info/METADATA
mosaik_gridcontrollers-0.3.dist-info/WHEEL
mosaik_gridcontrollers-0.3.dist-info/top_level.txt
mosaik_gridcontrollers-0.3.dist-info/RECORD
