Metadata-Version: 2.1
Name: mosaik-gridcontrollers
Version: 0.3
Summary: A suite of controllers for power grids implemented as mosaik simulators.
Home-page: https://gitlab.com/mosaik/mosaik-gridcontrollers
Author: Reef Eilers
Author-email: reef.eilers@offis.de
License: UNKNOWN
Platform: UNKNOWN
Classifier: Development Status :: 3 - Alpha
Classifier: Environment :: Console
Classifier: Intended Audience :: Science/Research
Classifier: License :: OSI Approved :: GNU Lesser General Public License v2 (LGPLv2)
Classifier: Natural Language :: English
Classifier: Operating System :: OS Independent
Classifier: Programming Language :: Python
Classifier: Programming Language :: Python :: 3
Classifier: Programming Language :: Python :: 3.7
Classifier: Programming Language :: Python :: 3.8
Classifier: Programming Language :: Python :: 3.9
Classifier: Topic :: Scientific/Engineering
Requires-Dist: numpy (>=1.2)
Requires-Dist: mosaik-api (>=2.4)
Requires-Dist: mosaik (>=2.6)
